{"version":1,"meta":{"run_name":"2026-02-05_13-21-14","units":"in","robot":{"width":12,"height":12},"log_hz":8},"thinning":{"raw":314,"kept":314,"removed":0,"viewer_thin_ms":1,"xy_tol":1.5,"theta_tol":35.0},"poses":[{"t":12723,"x":50.0,"y":6.0,"theta":180.0,"l_vel":-0.0,"r_vel":0.0,"speed":0.0},{"t":12843,"x":48.36,"y":5.94,"theta":180.07,"l_vel":44.4,"r_vel":36.9,"speed":40.65},{"t":12963,"x":44.94,"y":6.07,"theta":180.1,"l_vel":67.1,"r_vel":69.8,"speed":68.44999999999999},{"t":13083,"x":39.73,"y":6.19,"theta":179.38,"l_vel":79.3,"r_vel":84.4,"speed":81.85},{"t":13203,"x":35.12,"y":6.16,"theta":178.82,"l_vel":74.7,"r_vel":69.6,"speed":72.15},{"t":13323,"x":31.31,"y":6.08,"theta":179.02,"l_vel":57.9,"r_vel":57.3,"speed":57.599999999999994},{"t":13443,"x":29.41,"y":6.07,"theta":178.82,"l_vel":9.4,"r_vel":9.7,"speed":9.55},{"t":13563,"x":29.44,"y":6.11,"theta":178.93,"l_vel":-2.8,"r_vel":-2.5,"speed":2.65},{"t":13683,"x":29.5,"y":6.11,"theta":178.76,"l_vel":48.8,"r_vel":-25.7,"speed":37.25},{"t":13803,"x":27.86,"y":6.04,"theta":190.3,"l_vel":39.5,"r_vel":-44.5,"speed":42.0},{"t":13923,"x":27.15,"y":6.02,"theta":215.78,"l_vel":56.0,"r_vel":-57.0,"speed":56.5},{"t":14043,"x":26.73,"y":5.97,"theta":249.55,"l_vel":20.8,"r_vel":-20.2,"speed":20.5},{"t":14163,"x":26.84,"y":4.42,"theta":267.53,"l_vel":-1.6,"r_vel":-2.4,"speed":2.0},{"t":14283,"x":26.8,"y":5.06,"theta":267.54,"l_vel":5.1,"r_vel":-3.0,"speed":4.05},{"t":14403,"x":26.79,"y":4.8,"theta":268.97,"l_vel":-0.0,"r_vel":1.7,"speed":0.85},{"t":14523,"x":26.78,"y":5.14,"theta":268.93,"l_vel":10.2,"r_vel":-5.2,"speed":7.699999999999999},{"t":14643,"x":26.78,"y":5.14,"theta":269.0,"l_vel":-0.0,"r_vel":20.2,"speed":10.1},{"t":14763,"x":26.72,"y":5.23,"theta":267.8,"l_vel":-0.0,"r_vel":8.2,"speed":4.1},{"t":14883,"x":26.68,"y":5.36,"theta":266.55,"l_vel":1.7,"r_vel":10.4,"speed":6.05},{"t":15003,"x":26.6,"y":5.94,"theta":264.76,"l_vel":13.4,"r_vel":12.3,"speed":12.850000000000001},{"t":15123,"x":26.45,"y":6.95,"theta":263.45,"l_vel":11.4,"r_vel":13.2,"speed":12.3},{"t":15243,"x":26.28,"y":7.76,"theta":263.22,"l_vel":14.1,"r_vel":15.1,"speed":14.6},{"t":15363,"x":26.07,"y":8.77,"theta":263.05,"l_vel":17.7,"r_vel":18.0,"speed":17.85},{"t":15483,"x":25.86,"y":9.91,"theta":263.09,"l_vel":18.4,"r_vel":17.8,"speed":18.1},{"t":15603,"x":25.62,"y":11.13,"theta":263.31,"l_vel":19.3,"r_vel":17.1,"speed":18.200000000000003},{"t":15723,"x":25.41,"y":12.32,"theta":263.41,"l_vel":19.6,"r_vel":16.5,"speed":18.05},{"t":15843,"x":25.24,"y":13.47,"theta":263.76,"l_vel":19.3,"r_vel":17.7,"speed":18.5},{"t":15963,"x":25.08,"y":14.63,"theta":263.91,"l_vel":19.1,"r_vel":18.9,"speed":19.0},{"t":16083,"x":24.94,"y":15.81,"theta":264.04,"l_vel":17.8,"r_vel":19.1,"speed":18.450000000000003},{"t":16203,"x":24.77,"y":16.97,"theta":263.61,"l_vel":19.5,"r_vel":14.4,"speed":16.95},{"t":16323,"x":24.56,"y":18.56,"theta":264.28,"l_vel":37.4,"r_vel":33.8,"speed":35.599999999999994},{"t":16443,"x":24.34,"y":21.01,"theta":264.95,"l_vel":41.1,"r_vel":40.4,"speed":40.75},{"t":16563,"x":24.16,"y":23.28,"theta":266.0,"l_vel":23.9,"r_vel":24.9,"speed":24.4},{"t":16683,"x":24.07,"y":24.76,"theta":266.79,"l_vel":14.3,"r_vel":13.6,"speed":13.95},{"t":16803,"x":24.05,"y":25.18,"theta":267.04,"l_vel":3.5,"r_vel":4.0,"speed":3.75},{"t":16923,"x":24.05,"y":25.21,"theta":266.97,"l_vel":27.1,"r_vel":-19.6,"speed":23.35},{"t":17043,"x":23.91,"y":27.0,"theta":273.75,"l_vel":35.7,"r_vel":-35.3,"speed":35.5},{"t":17163,"x":23.75,"y":27.64,"theta":297.19,"l_vel":25.2,"r_vel":-17.4,"speed":21.299999999999997},{"t":17283,"x":22.71,"y":26.49,"theta":314.2,"l_vel":-10.7,"r_vel":4.6,"speed":7.6499999999999995},{"t":17403,"x":23.19,"y":27.02,"theta":312.87,"l_vel":4.4,"r_vel":-3.8,"speed":4.1},{"t":17523,"x":22.9,"y":26.72,"theta":314.59,"l_vel":-8.1,"r_vel":5.4,"speed":6.75},{"t":17643,"x":23.39,"y":27.38,"theta":314.32,"l_vel":21.3,"r_vel":17.7,"speed":19.5},{"t":17763,"x":24.7,"y":28.65,"theta":314.8,"l_vel":38.7,"r_vel":38.1,"speed":38.400000000000006},{"t":17883,"x":26.98,"y":30.76,"theta":314.72,"l_vel":50.4,"r_vel":51.7,"speed":51.05},{"t":18003,"x":29.11,"y":32.73,"theta":314.43,"l_vel":52.2,"r_vel":55.9,"speed":54.05},{"t":18123,"x":31.61,"y":35.13,"theta":314.06,"l_vel":54.4,"r_vel":55.3,"speed":54.849999999999994},{"t":18243,"x":34.34,"y":37.89,"theta":313.78,"l_vel":57.6,"r_vel":58.7,"speed":58.150000000000006},{"t":18363,"x":36.7,"y":40.3,"theta":313.62,"l_vel":57.6,"r_vel":55.8,"speed":56.7},{"t":18483,"x":39.19,"y":42.89,"theta":313.49,"l_vel":55.8,"r_vel":53.5,"speed":54.65},{"t":18603,"x":41.86,"y":45.7,"theta":313.36,"l_vel":57.0,"r_vel":57.6,"speed":57.3},{"t":18723,"x":43.69,"y":47.6,"theta":313.17,"l_vel":46.1,"r_vel":41.6,"speed":43.85},{"t":18843,"x":44.98,"y":48.96,"theta":313.14,"l_vel":14.4,"r_vel":16.5,"speed":15.45},{"t":18963,"x":45.19,"y":49.19,"theta":312.94,"l_vel":5.4,"r_vel":6.0,"speed":5.7},{"t":19083,"x":45.19,"y":49.17,"theta":312.94,"l_vel":-0.0,"r_vel":0.0,"speed":0.0},{"t":19203,"x":45.06,"y":49.01,"theta":315.2,"l_vel":-0.0,"r_vel":-39.8,"speed":19.9},{"t":19323,"x":43.8,"y":48.12,"theta":325.85,"l_vel":-11.0,"r_vel":-54.0,"speed":32.5},{"t":19443,"x":42.08,"y":47.21,"theta":338.48,"l_vel":-13.1,"r_vel":-63.8,"speed":38.449999999999996},{"t":19563,"x":39.77,"y":46.73,"theta":354.18,"l_vel":-28.3,"r_vel":-66.3,"speed":47.3},{"t":19683,"x":35.6,"y":46.87,"theta":7.85,"l_vel":-51.5,"r_vel":-62.5,"speed":57.0},{"t":19803,"x":31.99,"y":47.48,"theta":11.21,"l_vel":-64.1,"r_vel":-69.6,"speed":66.85},{"t":19923,"x":28.11,"y":48.22,"theta":11.56,"l_vel":-42.8,"r_vel":-35.7,"speed":39.25},{"t":20043,"x":26.38,"y":48.79,"theta":5.89,"l_vel":-19.5,"r_vel":-4.4,"speed":11.95},{"t":20163,"x":26.11,"y":48.89,"theta":1.02,"l_vel":-4.5,"r_vel":1.1,"speed":2.8},{"t":20283,"x":25.92,"y":48.82,"theta":359.99,"l_vel":-2.8,"r_vel":-2.5,"speed":2.65},{"t":20403,"x":25.9,"y":48.81,"theta":359.9,"l_vel":-4.1,"r_vel":0.0,"speed":2.05},{"t":20523,"x":25.9,"y":48.81,"theta":359.91,"l_vel":-0.0,"r_vel":0.0,"speed":0.0},{"t":20643,"x":25.94,"y":48.81,"theta":0.12,"l_vel":2.9,"r_vel":0.0,"speed":1.45},{"t":20763,"x":25.94,"y":48.81,"theta":0.13,"l_vel":-0.0,"r_vel":0.0,"speed":0.0},{"t":20883,"x":25.69,"y":48.81,"theta":0.08,"l_vel":-14.5,"r_vel":-5.8,"speed":10.15},{"t":21003,"x":24.58,"y":48.82,"theta":359.56,"l_vel":-12.6,"r_vel":-7.3,"speed":9.95},{"t":21123,"x":24.11,"y":48.82,"theta":359.5,"l_vel":-4.4,"r_vel":-2.3,"speed":3.35},{"t":21243,"x":23.88,"y":48.81,"theta":359.51,"l_vel":-4.9,"r_vel":0.0,"speed":2.45},{"t":21363,"x":23.86,"y":48.81,"theta":359.5,"l_vel":-4.6,"r_vel":0.0,"speed":2.3},{"t":21483,"x":23.86,"y":48.81,"theta":359.5,"l_vel":-0.0,"r_vel":0.0,"speed":0.0},{"t":21603,"x":23.86,"y":48.81,"theta":359.5,"l_vel":-0.0,"r_vel":0.0,"speed":0.0},{"t":21723,"x":23.86,"y":48.81,"theta":359.5,"l_vel":-0.0,"r_vel":0.0,"speed":0.0},{"t":21843,"x":23.86,"y":48.81,"theta":359.49,"l_vel":-0.0,"r_vel":0.0,"speed":0.0},{"t":21963,"x":24.01,"y":48.82,"theta":359.89,"l_vel":3.5,"r_vel":3.1,"speed":3.3},{"t":22083,"x":24.04,"y":48.82,"theta":359.75,"l_vel":2.3,"r_vel":0.0,"speed":1.15},{"t":23283,"x":21.98,"y":49.02,"theta":359.51,"l_vel":3.8,"r_vel":2.9,"speed":3.3499999999999996},{"t":23403,"x":21.99,"y":49.02,"theta":359.5,"l_vel":-0.0,"r_vel":0.0,"speed":0.0},{"t":23523,"x":21.99,"y":49.02,"theta":359.48,"l_vel":-0.0,"r_vel":0.0,"speed":0.0},{"t":23643,"x":21.99,"y":49.02,"theta":359.49,"l_vel":-0.0,"r_vel":0.0,"speed":0.0},{"t":23763,"x":22.0,"y":49.02,"theta":359.5,"l_vel":5.3,"r_vel":0.0,"speed":2.65},{"t":23883,"x":22.0,"y":49.02,"theta":359.53,"l_vel":-0.0,"r_vel":0.0,"speed":0.0},{"t":24003,"x":22.0,"y":49.02,"theta":359.51,"l_vel":-0.0,"r_vel":0.0,"speed":0.0},{"t":24123,"x":22.0,"y":49.02,"theta":359.54,"l_vel":-0.0,"r_vel":0.0,"speed":0.0},{"t":24243,"x":22.0,"y":49.02,"theta":359.54,"l_vel":-0.0,"r_vel":0.0,"speed":0.0},{"t":24363,"x":22.0,"y":49.02,"theta":359.54,"l_vel":-0.0,"r_vel":0.0,"speed":0.0},{"t":24483,"x":22.0,"y":49.02,"theta":359.53,"l_vel":-0.0,"r_vel":0.0,"speed":0.0},{"t":24603,"x":22.0,"y":49.02,"theta":359.55,"l_vel":-0.0,"r_vel":0.0,"speed":0.0},{"t":24723,"x":22.0,"y":49.02,"theta":359.55,"l_vel":-0.0,"r_vel":0.0,"speed":0.0},{"t":24843,"x":22.0,"y":49.02,"theta":359.55,"l_vel":-0.0,"r_vel":0.0,"speed":0.0},{"t":24963,"x":22.0,"y":49.02,"theta":359.55,"l_vel":-0.0,"r_vel":0.0,"speed":0.0},{"t":25083,"x":22.0,"y":49.02,"theta":359.55,"l_vel":-0.0,"r_vel":0.0,"speed":0.0},{"t":25203,"x":22.0,"y":49.02,"theta":359.56,"l_vel":-0.0,"r_vel":0.0,"speed":0.0},{"t":25323,"x":21.99,"y":49.02,"theta":359.57,"l_vel":-0.0,"r_vel":0.0,"speed":0.0},{"t":25443,"x":21.99,"y":49.02,"theta":359.57,"l_vel":-0.0,"r_vel":0.0,"speed":0.0},{"t":25563,"x":21.99,"y":49.02,"theta":359.58,"l_vel":-0.0,"r_vel":0.0,"speed":0.0},{"t":25683,"x":21.99,"y":49.02,"theta":359.57,"l_vel":-0.0,"r_vel":0.0,"speed":0.0},{"t":25803,"x":21.99,"y":49.02,"theta":359.56,"l_vel":-0.0,"r_vel":0.0,"speed":0.0},{"t":25923,"x":21.99,"y":49.02,"theta":359.57,"l_vel":-0.0,"r_vel":0.0,"speed":0.0},{"t":26043,"x":21.99,"y":49.02,"theta":359.57,"l_vel":-0.0,"r_vel":0.0,"speed":0.0},{"t":26163,"x":21.99,"y":49.02,"theta":359.57,"l_vel":-0.0,"r_vel":0.0,"speed":0.0},{"t":26283,"x":21.99,"y":49.02,"theta":359.57,"l_vel":-0.0,"r_vel":0.0,"speed":0.0},{"t":26403,"x":21.99,"y":49.02,"theta":359.56,"l_vel":-0.0,"r_vel":0.0,"speed":0.0},{"t":26523,"x":21.99,"y":49.02,"theta":359.57,"l_vel":-0.0,"r_vel":0.0,"speed":0.0},{"t":26643,"x":21.99,"y":49.02,"theta":359.57,"l_vel":-0.0,"r_vel":0.0,"speed":0.0},{"t":26763,"x":21.99,"y":49.02,"theta":359.57,"l_vel":-0.0,"r_vel":0.0,"speed":0.0},{"t":26883,"x":21.99,"y":49.02,"theta":359.57,"l_vel":-0.0,"r_vel":0.0,"speed":0.0},{"t":27003,"x":21.99,"y":49.02,"theta":359.57,"l_vel":-0.0,"r_vel":0.0,"speed":0.0},{"t":27123,"x":21.99,"y":49.02,"theta":359.57,"l_vel":-0.0,"r_vel":0.0,"speed":0.0},{"t":27243,"x":21.99,"y":49.02,"theta":359.58,"l_vel":-0.0,"r_vel":0.0,"speed":0.0},{"t":27363,"x":21.99,"y":49.02,"theta":359.57,"l_vel":-0.0,"r_vel":0.0,"speed":0.0},{"t":27483,"x":21.99,"y":49.02,"theta":359.57,"l_vel":-0.0,"r_vel":0.0,"speed":0.0},{"t":27603,"x":21.99,"y":49.02,"theta":359.56,"l_vel":-0.0,"r_vel":0.0,"speed":0.0},{"t":27723,"x":21.99,"y":49.02,"theta":359.56,"l_vel":-0.0,"r_vel":0.0,"speed":0.0},{"t":27843,"x":21.99,"y":49.02,"theta":359.56,"l_vel":-0.0,"r_vel":0.0,"speed":0.0},{"t":27963,"x":22.0,"y":49.02,"theta":359.56,"l_vel":-0.0,"r_vel":0.0,"speed":0.0},{"t":28083,"x":22.0,"y":49.02,"theta":359.56,"l_vel":-0.0,"r_vel":0.0,"speed":0.0},{"t":28203,"x":22.0,"y":49.02,"theta":359.56,"l_vel":-0.0,"r_vel":0.0,"speed":0.0},{"t":28323,"x":22.0,"y":49.02,"theta":359.55,"l_vel":-0.0,"r_vel":0.0,"speed":0.0},{"t":28443,"x":21.99,"y":49.02,"theta":359.56,"l_vel":-0.0,"r_vel":0.0,"speed":0.0},{"t":28563,"x":22.0,"y":49.02,"theta":359.56,"l_vel":-0.0,"r_vel":0.0,"speed":0.0},{"t":28683,"x":22.0,"y":49.02,"theta":359.55,"l_vel":-0.0,"r_vel":0.0,"speed":0.0},{"t":28803,"x":22.36,"y":49.02,"theta":359.57,"l_vel":42.8,"r_vel":25.8,"speed":34.3},{"t":28923,"x":23.35,"y":49.03,"theta":0.13,"l_vel":24.3,"r_vel":24.0,"speed":24.15},{"t":29043,"x":25.64,"y":48.97,"theta":0.03,"l_vel":36.6,"r_vel":37.6,"speed":37.1},{"t":29163,"x":28.37,"y":48.87,"theta":359.91,"l_vel":42.9,"r_vel":44.7,"speed":43.8},{"t":29283,"x":31.01,"y":48.82,"theta":359.62,"l_vel":44.1,"r_vel":45.6,"speed":44.85},{"t":29403,"x":34.25,"y":48.77,"theta":359.41,"l_vel":46.9,"r_vel":45.0,"speed":45.95},{"t":29523,"x":37.27,"y":48.76,"theta":359.15,"l_vel":46.6,"r_vel":49.4,"speed":48.0},{"t":29643,"x":40.13,"y":48.8,"theta":359.22,"l_vel":47.9,"r_vel":49.0,"speed":48.45},{"t":29763,"x":43.53,"y":48.81,"theta":359.16,"l_vel":46.6,"r_vel":48.7,"speed":47.650000000000006},{"t":29883,"x":46.67,"y":48.85,"theta":359.31,"l_vel":47.6,"r_vel":48.4,"speed":48.0},{"t":30003,"x":49.16,"y":48.87,"theta":359.72,"l_vel":36.9,"r_vel":39.2,"speed":38.05},{"t":30125,"x":51.07,"y":48.81,"theta":358.67,"l_vel":6.9,"r_vel":5.4,"speed":6.15},{"t":30245,"x":51.42,"y":48.79,"theta":358.99,"l_vel":9.3,"r_vel":12.3,"speed":10.8},{"t":30365,"x":51.74,"y":48.83,"theta":358.43,"l_vel":9.2,"r_vel":7.3,"speed":8.25},{"t":30485,"x":51.86,"y":48.83,"theta":358.42,"l_vel":2.8,"r_vel":3.9,"speed":3.3499999999999996},{"t":30605,"x":51.91,"y":48.83,"theta":358.33,"l_vel":13.8,"r_vel":3.9,"speed":8.85},{"t":30725,"x":51.95,"y":48.83,"theta":358.43,"l_vel":12.1,"r_vel":14.5,"speed":13.3},{"t":30845,"x":51.97,"y":48.83,"theta":358.45,"l_vel":71.8,"r_vel":5.5,"speed":38.65},{"t":30965,"x":51.97,"y":48.83,"theta":358.42,"l_vel":-0.0,"r_vel":0.0,"speed":0.0},{"t":31085,"x":52.0,"y":48.83,"theta":358.4,"l_vel":3.0,"r_vel":7.2,"speed":5.1},{"t":31205,"x":52.01,"y":48.83,"theta":358.46,"l_vel":-0.0,"r_vel":0.0,"speed":0.0},{"t":31325,"x":52.03,"y":48.83,"theta":358.41,"l_vel":-0.0,"r_vel":2.3,"speed":1.15},{"t":31445,"x":52.07,"y":48.83,"theta":358.4,"l_vel":6.9,"r_vel":0.0,"speed":3.45},{"t":31565,"x":52.07,"y":48.83,"theta":358.39,"l_vel":-0.0,"r_vel":1.6,"speed":0.8},{"t":31685,"x":58.64,"y":48.97,"theta":358.24,"l_vel":-5.9,"r_vel":-5.8,"speed":5.85},{"t":31805,"x":58.56,"y":48.97,"theta":358.28,"l_vel":-3.1,"r_vel":-3.4,"speed":3.25},{"t":31925,"x":58.56,"y":48.97,"theta":358.24,"l_vel":-0.0,"r_vel":0.0,"speed":0.0},{"t":32045,"x":58.56,"y":48.97,"theta":358.22,"l_vel":-0.0,"r_vel":0.0,"speed":0.0},{"t":32165,"x":58.55,"y":48.97,"theta":358.22,"l_vel":-0.0,"r_vel":0.0,"speed":0.0},{"t":32285,"x":58.54,"y":48.97,"theta":358.2,"l_vel":-3.8,"r_vel":0.0,"speed":1.9},{"t":32405,"x":58.54,"y":48.97,"theta":358.2,"l_vel":-0.0,"r_vel":0.0,"speed":0.0},{"t":32525,"x":58.54,"y":48.97,"theta":358.2,"l_vel":-0.0,"r_vel":-10.2,"speed":5.1},{"t":32645,"x":58.54,"y":48.97,"theta":358.18,"l_vel":-0.0,"r_vel":0.0,"speed":0.0},{"t":32765,"x":58.54,"y":48.97,"theta":358.18,"l_vel":-0.0,"r_vel":0.0,"speed":0.0},{"t":32885,"x":58.55,"y":48.97,"theta":358.16,"l_vel":-0.0,"r_vel":0.0,"speed":0.0},{"t":33005,"x":58.55,"y":48.97,"theta":358.16,"l_vel":-0.0,"r_vel":0.0,"speed":0.0},{"t":33125,"x":58.55,"y":48.97,"theta":358.15,"l_vel":-0.0,"r_vel":-1.7,"speed":0.85},{"t":33245,"x":58.55,"y":48.97,"theta":358.12,"l_vel":-0.0,"r_vel":0.0,"speed":0.0},{"t":33365,"x":58.55,"y":48.97,"theta":358.13,"l_vel":-0.0,"r_vel":0.0,"speed":0.0},{"t":33485,"x":58.54,"y":48.97,"theta":358.11,"l_vel":-40.6,"r_vel":0.0,"speed":20.3},{"t":33605,"x":58.54,"y":48.97,"theta":358.09,"l_vel":-40.6,"r_vel":0.0,"speed":20.3},{"t":33725,"x":58.53,"y":48.97,"theta":358.12,"l_vel":-0.0,"r_vel":0.0,"speed":0.0},{"t":33845,"x":58.53,"y":48.97,"theta":358.11,"l_vel":-0.0,"r_vel":0.0,"speed":0.0},{"t":33965,"x":58.53,"y":48.97,"theta":358.12,"l_vel":-0.0,"r_vel":0.0,"speed":0.0},{"t":34085,"x":58.53,"y":48.96,"theta":358.14,"l_vel":-0.0,"r_vel":0.0,"speed":0.0},{"t":34205,"x":58.53,"y":48.97,"theta":358.13,"l_vel":-0.0,"r_vel":0.0,"speed":0.0},{"t":34325,"x":58.53,"y":48.96,"theta":358.14,"l_vel":-0.0,"r_vel":0.0,"speed":0.0},{"t":34445,"x":58.53,"y":48.97,"theta":358.12,"l_vel":-0.0,"r_vel":0.0,"speed":0.0},{"t":34565,"x":58.54,"y":48.97,"theta":358.11,"l_vel":-0.0,"r_vel":0.0,"speed":0.0},{"t":34685,"x":58.54,"y":48.97,"theta":358.09,"l_vel":-0.0,"r_vel":0.0,"speed":0.0},{"t":34805,"x":58.54,"y":48.97,"theta":358.09,"l_vel":-0.0,"r_vel":0.0,"speed":0.0},{"t":34925,"x":58.54,"y":48.97,"theta":358.09,"l_vel":-0.0,"r_vel":0.0,"speed":0.0},{"t":35045,"x":58.54,"y":48.97,"theta":358.1,"l_vel":-0.0,"r_vel":0.0,"speed":0.0},{"t":35165,"x":58.54,"y":48.97,"theta":358.07,"l_vel":-0.0,"r_vel":0.0,"speed":0.0},{"t":35285,"x":58.54,"y":48.97,"theta":358.09,"l_vel":-0.0,"r_vel":0.0,"speed":0.0},{"t":35405,"x":58.54,"y":48.97,"theta":358.09,"l_vel":-0.0,"r_vel":0.0,"speed":0.0},{"t":35525,"x":58.54,"y":48.97,"theta":358.09,"l_vel":-0.0,"r_vel":0.0,"speed":0.0},{"t":35645,"x":58.54,"y":48.97,"theta":358.1,"l_vel":-0.0,"r_vel":0.0,"speed":0.0},{"t":35765,"x":58.54,"y":48.97,"theta":358.08,"l_vel":-0.0,"r_vel":0.0,"speed":0.0},{"t":35885,"x":58.54,"y":48.97,"theta":358.09,"l_vel":-0.0,"r_vel":0.0,"speed":0.0},{"t":36005,"x":58.54,"y":48.97,"theta":358.08,"l_vel":-0.0,"r_vel":0.0,"speed":0.0},{"t":36125,"x":58.54,"y":48.97,"theta":358.08,"l_vel":-0.0,"r_vel":0.0,"speed":0.0},{"t":36245,"x":58.54,"y":48.97,"theta":358.1,"l_vel":-0.0,"r_vel":0.0,"speed":0.0},{"t":36365,"x":58.54,"y":48.97,"theta":358.09,"l_vel":-0.0,"r_vel":0.0,"speed":0.0},{"t":36485,"x":58.54,"y":48.97,"theta":358.08,"l_vel":-0.0,"r_vel":0.0,"speed":0.0},{"t":36605,"x":58.54,"y":48.97,"theta":358.08,"l_vel":-0.0,"r_vel":0.0,"speed":0.0},{"t":36725,"x":58.54,"y":48.97,"theta":358.09,"l_vel":-0.0,"r_vel":0.0,"speed":0.0},{"t":36845,"x":58.54,"y":48.97,"theta":358.09,"l_vel":-0.0,"r_vel":0.0,"speed":0.0},{"t":36965,"x":58.54,"y":48.97,"theta":358.09,"l_vel":-0.0,"r_vel":0.0,"speed":0.0},{"t":37085,"x":58.54,"y":48.97,"theta":358.09,"l_vel":-0.0,"r_vel":0.0,"speed":0.0},{"t":37205,"x":58.54,"y":48.97,"theta":358.09,"l_vel":-0.0,"r_vel":0.0,"speed":0.0},{"t":37325,"x":58.54,"y":48.97,"theta":358.09,"l_vel":-0.0,"r_vel":0.0,"speed":0.0},{"t":37445,"x":58.54,"y":48.97,"theta":358.11,"l_vel":-0.0,"r_vel":0.0,"speed":0.0},{"t":37565,"x":58.54,"y":48.97,"theta":358.09,"l_vel":-0.0,"r_vel":0.0,"speed":0.0},{"t":37685,"x":57.35,"y":48.9,"theta":358.9,"l_vel":-19.9,"r_vel":-26.3,"speed":23.1},{"t":37805,"x":55.0,"y":48.9,"theta":359.54,"l_vel":-48.6,"r_vel":-49.8,"speed":49.2},{"t":37925,"x":51.54,"y":48.94,"theta":359.75,"l_vel":-54.1,"r_vel":-55.5,"speed":54.8},{"t":38045,"x":47.33,"y":48.98,"theta":359.72,"l_vel":-60.5,"r_vel":-64.0,"speed":62.25},{"t":38165,"x":43.05,"y":48.96,"theta":359.92,"l_vel":-69.4,"r_vel":-67.2,"speed":68.30000000000001},{"t":38285,"x":38.43,"y":48.96,"theta":0.0,"l_vel":-68.2,"r_vel":-68.4,"speed":68.30000000000001},{"t":38405,"x":33.94,"y":48.96,"theta":0.02,"l_vel":-71.6,"r_vel":-71.5,"speed":71.55},{"t":38525,"x":29.75,"y":49.01,"theta":0.02,"l_vel":-45.4,"r_vel":-48.5,"speed":46.95},{"t":38645,"x":27.29,"y":48.93,"theta":0.54,"l_vel":-18.7,"r_vel":-16.8,"speed":17.75},{"t":38765,"x":25.93,"y":48.95,"theta":359.83,"l_vel":-20.7,"r_vel":-44.7,"speed":32.7},{"t":38885,"x":25.77,"y":48.86,"theta":359.17,"l_vel":-5.3,"r_vel":-38.4,"speed":21.849999999999998},{"t":39005,"x":25.71,"y":48.86,"theta":359.14,"l_vel":-2.2,"r_vel":-21.3,"speed":11.75},{"t":39125,"x":25.71,"y":48.86,"theta":359.13,"l_vel":-0.0,"r_vel":-21.6,"speed":10.8},{"t":39245,"x":25.7,"y":48.86,"theta":359.12,"l_vel":-1.5,"r_vel":-23.4,"speed":12.45},{"t":39365,"x":25.7,"y":48.86,"theta":359.12,"l_vel":-0.0,"r_vel":-23.5,"speed":11.75},{"t":39485,"x":25.7,"y":48.86,"theta":359.13,"l_vel":-0.0,"r_vel":-21.6,"speed":10.8},{"t":40805,"x":22.0,"y":49.0,"theta":358.91,"l_vel":-0.0,"r_vel":0.0,"speed":0.0},{"t":40925,"x":22.0,"y":49.0,"theta":358.92,"l_vel":-0.0,"r_vel":0.0,"speed":0.0},{"t":41045,"x":22.0,"y":49.0,"theta":358.93,"l_vel":-0.0,"r_vel":0.0,"speed":0.0},{"t":41165,"x":22.0,"y":49.0,"theta":358.93,"l_vel":-0.0,"r_vel":0.0,"speed":0.0},{"t":41285,"x":22.0,"y":49.0,"theta":358.93,"l_vel":-0.0,"r_vel":0.0,"speed":0.0},{"t":41405,"x":22.0,"y":49.0,"theta":358.94,"l_vel":-0.0,"r_vel":0.0,"speed":0.0},{"t":41525,"x":22.0,"y":49.0,"theta":358.94,"l_vel":-0.0,"r_vel":0.0,"speed":0.0},{"t":41645,"x":22.0,"y":49.0,"theta":358.94,"l_vel":-0.0,"r_vel":0.0,"speed":0.0},{"t":41765,"x":22.0,"y":49.0,"theta":358.93,"l_vel":-0.0,"r_vel":0.0,"speed":0.0},{"t":41885,"x":22.0,"y":49.0,"theta":358.92,"l_vel":-0.0,"r_vel":0.0,"speed":0.0},{"t":42005,"x":22.0,"y":49.0,"theta":358.92,"l_vel":-0.0,"r_vel":0.0,"speed":0.0},{"t":42125,"x":22.0,"y":49.0,"theta":358.93,"l_vel":-0.0,"r_vel":0.0,"speed":0.0},{"t":42245,"x":22.0,"y":49.0,"theta":358.92,"l_vel":-0.0,"r_vel":0.0,"speed":0.0},{"t":42365,"x":22.0,"y":49.0,"theta":358.91,"l_vel":-0.0,"r_vel":0.0,"speed":0.0},{"t":42485,"x":22.0,"y":49.0,"theta":358.91,"l_vel":-0.0,"r_vel":0.0,"speed":0.0},{"t":42605,"x":22.0,"y":49.0,"theta":358.92,"l_vel":-0.0,"r_vel":0.0,"speed":0.0},{"t":42725,"x":22.0,"y":49.0,"theta":358.92,"l_vel":-0.0,"r_vel":0.0,"speed":0.0},{"t":42845,"x":22.0,"y":49.0,"theta":358.91,"l_vel":-0.0,"r_vel":0.0,"speed":0.0},{"t":42965,"x":22.0,"y":49.0,"theta":358.92,"l_vel":-0.0,"r_vel":0.0,"speed":0.0},{"t":43085,"x":22.0,"y":49.0,"theta":358.92,"l_vel":-0.0,"r_vel":0.0,"speed":0.0},{"t":43205,"x":22.0,"y":49.0,"theta":358.93,"l_vel":-0.0,"r_vel":0.0,"speed":0.0},{"t":43325,"x":22.0,"y":49.0,"theta":358.94,"l_vel":-0.0,"r_vel":0.0,"speed":0.0},{"t":43445,"x":22.0,"y":49.0,"theta":358.95,"l_vel":-0.0,"r_vel":0.0,"speed":0.0},{"t":43565,"x":22.0,"y":49.0,"theta":358.96,"l_vel":-0.0,"r_vel":0.0,"speed":0.0},{"t":43685,"x":22.0,"y":49.0,"theta":358.95,"l_vel":-0.0,"r_vel":0.0,"speed":0.0},{"t":43805,"x":22.0,"y":49.0,"theta":358.95,"l_vel":-0.0,"r_vel":0.0,"speed":0.0},{"t":43925,"x":22.0,"y":49.0,"theta":358.93,"l_vel":-0.0,"r_vel":0.0,"speed":0.0},{"t":44045,"x":22.0,"y":49.0,"theta":358.93,"l_vel":-0.0,"r_vel":0.0,"speed":0.0},{"t":44165,"x":22.0,"y":49.0,"theta":358.92,"l_vel":-0.0,"r_vel":0.0,"speed":0.0},{"t":44285,"x":22.0,"y":49.0,"theta":358.93,"l_vel":-0.0,"r_vel":0.0,"speed":0.0},{"t":44405,"x":22.0,"y":49.0,"theta":358.94,"l_vel":-0.0,"r_vel":0.0,"speed":0.0},{"t":44525,"x":22.0,"y":49.0,"theta":358.93,"l_vel":-0.0,"r_vel":0.0,"speed":0.0},{"t":44645,"x":22.0,"y":49.0,"theta":358.92,"l_vel":-0.0,"r_vel":0.0,"speed":0.0},{"t":44765,"x":22.0,"y":49.0,"theta":358.92,"l_vel":-0.0,"r_vel":0.0,"speed":0.0},{"t":44885,"x":22.0,"y":49.0,"theta":358.92,"l_vel":-0.0,"r_vel":0.0,"speed":0.0},{"t":45005,"x":22.0,"y":49.0,"theta":358.91,"l_vel":-0.0,"r_vel":0.0,"speed":0.0},{"t":45125,"x":22.0,"y":49.0,"theta":358.9,"l_vel":-0.0,"r_vel":0.0,"speed":0.0},{"t":45245,"x":22.0,"y":49.0,"theta":358.91,"l_vel":-0.0,"r_vel":0.0,"speed":0.0},{"t":45365,"x":22.0,"y":49.0,"theta":358.9,"l_vel":-0.0,"r_vel":0.0,"speed":0.0},{"t":45485,"x":22.0,"y":49.0,"theta":358.92,"l_vel":-0.0,"r_vel":0.0,"speed":0.0},{"t":45605,"x":22.0,"y":49.0,"theta":358.92,"l_vel":-0.0,"r_vel":0.0,"speed":0.0},{"t":45725,"x":22.0,"y":49.0,"theta":358.93,"l_vel":-0.0,"r_vel":0.0,"speed":0.0},{"t":45845,"x":22.0,"y":49.0,"theta":358.92,"l_vel":-0.0,"r_vel":0.0,"speed":0.0},{"t":45965,"x":22.0,"y":49.0,"theta":358.92,"l_vel":-0.0,"r_vel":0.0,"speed":0.0},{"t":46085,"x":22.0,"y":49.0,"theta":358.93,"l_vel":-0.0,"r_vel":0.0,"speed":0.0},{"t":46205,"x":22.0,"y":49.0,"theta":358.94,"l_vel":-0.0,"r_vel":0.0,"speed":0.0},{"t":46325,"x":22.0,"y":49.0,"theta":358.93,"l_vel":-0.0,"r_vel":0.0,"speed":0.0},{"t":46445,"x":22.0,"y":49.0,"theta":358.94,"l_vel":-0.0,"r_vel":0.0,"speed":0.0},{"t":46565,"x":22.0,"y":49.0,"theta":358.93,"l_vel":-0.0,"r_vel":0.0,"speed":0.0},{"t":46685,"x":22.0,"y":49.0,"theta":358.93,"l_vel":-0.0,"r_vel":0.0,"speed":0.0},{"t":46805,"x":22.0,"y":49.0,"theta":358.94,"l_vel":-0.0,"r_vel":0.0,"speed":0.0},{"t":46925,"x":22.0,"y":49.0,"theta":358.92,"l_vel":-0.0,"r_vel":0.0,"speed":0.0},{"t":47045,"x":22.49,"y":49.01,"theta":358.97,"l_vel":24.8,"r_vel":26.2,"speed":25.5},{"t":47165,"x":23.72,"y":49.03,"theta":359.76,"l_vel":28.3,"r_vel":26.8,"speed":27.55},{"t":47285,"x":26.22,"y":49.11,"theta":0.13,"l_vel":39.3,"r_vel":36.2,"speed":37.75},{"t":47405,"x":28.76,"y":49.1,"theta":0.35,"l_vel":46.2,"r_vel":46.2,"speed":46.2},{"t":47525,"x":31.78,"y":49.08,"theta":0.37,"l_vel":47.9,"r_vel":48.4,"speed":48.15},{"t":47645,"x":35.13,"y":49.06,"theta":0.49,"l_vel":51.8,"r_vel":48.3,"speed":50.05},{"t":47765,"x":38.0,"y":49.04,"theta":0.45,"l_vel":49.9,"r_vel":51.4,"speed":50.65},{"t":47885,"x":41.37,"y":49.0,"theta":0.69,"l_vel":47.8,"r_vel":47.2,"speed":47.5},{"t":48005,"x":44.1,"y":48.97,"theta":1.15,"l_vel":40.4,"r_vel":39.4,"speed":39.9},{"t":48125,"x":45.29,"y":48.94,"theta":1.39,"l_vel":8.6,"r_vel":8.3,"speed":8.45},{"t":48245,"x":45.37,"y":48.94,"theta":1.42,"l_vel":5.5,"r_vel":4.3,"speed":4.9},{"t":48365,"x":45.06,"y":48.94,"theta":1.31,"l_vel":-25.0,"r_vel":-26.9,"speed":25.95},{"t":48485,"x":43.72,"y":48.94,"theta":0.65,"l_vel":-43.4,"r_vel":-45.8,"speed":44.599999999999994},{"t":48605,"x":40.28,"y":48.93,"theta":359.43,"l_vel":-58.2,"r_vel":-88.1,"speed":73.15},{"t":48725,"x":35.44,"y":48.86,"theta":359.06,"l_vel":-82.3,"r_vel":-83.4,"speed":82.85},{"t":48845,"x":30.22,"y":48.83,"theta":359.64,"l_vel":-95.9,"r_vel":-96.4,"speed":96.15},{"t":48965,"x":24.18,"y":48.81,"theta":359.81,"l_vel":-82.6,"r_vel":-90.0,"speed":86.3},{"t":49085,"x":20.25,"y":49.18,"theta":359.55,"l_vel":-24.2,"r_vel":-17.1,"speed":20.65},{"t":49205,"x":19.87,"y":49.04,"theta":357.32,"l_vel":-12.7,"r_vel":-9.8,"speed":11.25},{"t":49325,"x":19.61,"y":48.93,"theta":355.87,"l_vel":-1.8,"r_vel":-3.5,"speed":2.65},{"t":49445,"x":19.35,"y":48.69,"theta":357.14,"l_vel":-6.3,"r_vel":-2.9,"speed":4.6},{"t":49565,"x":19.28,"y":48.73,"theta":357.31,"l_vel":-2.8,"r_vel":-4.7,"speed":3.75},{"t":49685,"x":19.22,"y":48.71,"theta":357.48,"l_vel":-3.3,"r_vel":-4.4,"speed":3.85},{"t":49805,"x":20.9,"y":48.8,"theta":358.34,"l_vel":39.9,"r_vel":38.4,"speed":39.15},{"t":49925,"x":23.26,"y":48.84,"theta":359.49,"l_vel":48.7,"r_vel":64.9,"speed":56.800000000000004},{"t":50045,"x":27.31,"y":48.87,"theta":0.2,"l_vel":84.1,"r_vel":81.8,"speed":82.94999999999999},{"t":50165,"x":33.09,"y":48.86,"theta":359.76,"l_vel":92.5,"r_vel":91.3,"speed":91.9},{"t":50285,"x":38.67,"y":48.92,"theta":359.34,"l_vel":90.8,"r_vel":90.1,"speed":90.44999999999999},{"t":50405,"x":43.4,"y":48.96,"theta":359.62,"l_vel":52.5,"r_vel":54.1,"speed":53.3},{"t":50525,"x":45.72,"y":48.96,"theta":359.48,"l_vel":14.0,"r_vel":15.1,"speed":14.55},{"t":50645,"x":45.76,"y":48.94,"theta":359.54,"l_vel":-3.1,"r_vel":-1.4,"speed":2.25},{"t":50765,"x":46.53,"y":48.94,"theta":0.2,"l_vel":50.2,"r_vel":-18.6,"speed":34.400000000000006},{"t":50885,"x":48.19,"y":48.91,"theta":19.38,"l_vel":58.2,"r_vel":-55.1,"speed":56.650000000000006},{"t":51005,"x":48.47,"y":49.11,"theta":43.99,"l_vel":31.5,"r_vel":-56.6,"speed":44.05},{"t":51125,"x":47.9,"y":50.14,"theta":66.57,"l_vel":3.1,"r_vel":-14.3,"speed":8.700000000000001},{"t":51245,"x":47.76,"y":50.35,"theta":69.11,"l_vel":1.1,"r_vel":-4.3,"speed":2.7},{"t":51365,"x":47.9,"y":50.0,"theta":69.27,"l_vel":9.9,"r_vel":-1.1,"speed":5.5},{"t":51485,"x":47.91,"y":49.97,"theta":69.28,"l_vel":8.4,"r_vel":51.4,"speed":29.9},{"t":51605,"x":48.81,"y":47.94,"theta":70.0,"l_vel":53.2,"r_vel":44.2,"speed":48.7},{"t":51725,"x":50.05,"y":43.84,"theta":71.0,"l_vel":89.3,"r_vel":84.2,"speed":86.75},{"t":51845,"x":51.94,"y":37.96,"theta":71.67,"l_vel":107.6,"r_vel":107.4,"speed":107.5},{"t":51965,"x":54.03,"y":31.26,"theta":72.3,"l_vel":118.4,"r_vel":120.2,"speed":119.30000000000001},{"t":52085,"x":56.23,"y":23.99,"theta":72.91,"l_vel":121.6,"r_vel":115.3,"speed":118.44999999999999},{"t":52205,"x":58.37,"y":16.7,"theta":76.24,"l_vel":127.0,"r_vel":127.0,"speed":127.0},{"t":52325,"x":58.78,"y":10.51,"theta":91.06,"l_vel":99.7,"r_vel":36.8,"speed":68.25},{"t":52445,"x":58.75,"y":4.69,"theta":92.98,"l_vel":121.6,"r_vel":97.0,"speed":109.3},{"t":52565,"x":58.38,"y":-1.6,"theta":87.72,"l_vel":101.4,"r_vel":94.6,"speed":98.0}],"watches":[{"time":16083,"level":"INFO","label":"Tongue mech state","value":"true"},{"time":23163,"level":"INFO","label":"Stopper state","value":"true"},{"time":31685,"level":"INFO","label":"Stopper state","value":"false"},{"time":37685,"level":"INFO","label":"Tongue mech state","value":"false"},{"time":40805,"level":"INFO","label":"Stopper state","value":"true"},{"time":48365,"level":"INFO","label":"Stopper state","value":"false"}]}